paymentcheckout/CardCheck.py
paymentcheckout/PayeerCheck.py
paymentcheckout/QiwiCheck.py
paymentcheckout/WebMoneyCheck.py
paymentcheckout/YooMoneyCheck.py
paymentcheckout-2.0.dist-info/LICENSE
paymentcheckout-2.0.dist-info/METADATA
paymentcheckout-2.0.dist-info/WHEEL
paymentcheckout-2.0.dist-info/top_level.txt
paymentcheckout-2.0.dist-info/RECORD
