Metadata-Version: 2.1
Name: paymentcheckout
Version: 2.0
Summary: Payment verification for QIWI, Payeer, YooMoney, WebMoney and QIWI Virtual Bank Card.
Home-page: UNKNOWN
Author: Blazzerrr
License: MIT
Platform: UNKNOWN
Classifier: License :: OSI Approved :: MIT License
Classifier: Programming Language :: Python :: 3
Classifier: Programming Language :: Python :: 3.7
Requires-Dist: requests
